vial/__init__.py
vial/app.py
vial/context.py
vial/errors.py
vial/exceptions.py
vial/gateway.py
vial/json.py
vial/loggers.py
vial/middleware.py
vial/parsers.py
vial/py.typed
vial/request.py
vial/routes.py
vial/timestamps.py
vial/types.py
pyvial-1.3.0.dist-info/LICENSE
pyvial-1.3.0.dist-info/METADATA
pyvial-1.3.0.dist-info/WHEEL
pyvial-1.3.0.dist-info/RECORD
