Metadata-Version: 2.1
Name: pyvial
Version: 1.3.0
Summary: A micro web framework for AWS Lambda.
Home-page: https://github.com/michaeldimchuk/pyvial
License: Apache-2.0
Author: Michael Dimchuk
Author-email: michaeldimchuk@gmail.com
Maintainer: Michael Dimchuk
Maintainer-email: michaeldimchuk@gmail.com
Requires-Python: >=3.9,<4.0
Classifier: License :: OSI Approved :: Apache Software License
Classifier: Programming Language :: Python :: 3
Classifier: Programming Language :: Python :: 3.9
Classifier: Programming Language :: Python :: 3.10
Classifier: Programming Language :: Python :: 3.11
Project-URL: Repository, https://github.com/michaeldimchuk/pyvial
